LICENSE
MANIFEST.in
README.md
setup.py
django_staticflatpages.egg-info/PKG-INFO
django_staticflatpages.egg-info/SOURCES.txt
django_staticflatpages.egg-info/dependency_links.txt
django_staticflatpages.egg-info/not-zip-safe
django_staticflatpages.egg-info/requires.txt
django_staticflatpages.egg-info/top_level.txt
staticflatpages/__init__.py
staticflatpages/apps.py
staticflatpages/middleware.py
staticflatpages/models.py
staticflatpages/sitemaps.py
staticflatpages/util.py
staticflatpages/views.py
staticflatpages/tests/__init__.py
staticflatpages/tests/sitemaps.py
staticflatpages/tests/tests.py
staticflatpages/tests/urls.py